pivpnpy/__init__.py
pivpnpy/pivpn.py
pivpnpy-0.0.1.dist-info/LICENSE
pivpnpy-0.0.1.dist-info/METADATA
pivpnpy-0.0.1.dist-info/WHEEL
pivpnpy-0.0.1.dist-info/top_level.txt
pivpnpy-0.0.1.dist-info/RECORD
