Metadata-Version: 2.1
Name: pivpnpy
Version: 0.0.1
Summary: Thin python wrapper for the pivpn command-line tool
Author-email: m00ninite <m00ninitehub@protonmail.com>
Project-URL: Homepage, https://github.com/m00ninite/pivpnpy
Classifier: Programming Language :: Python :: 3
Classifier: License :: OSI Approved :: MIT License
Classifier: Operating System :: OS Independent
Requires-Python: >=3.6
License-File: LICENSE
